{
  "TSLA": {
    "price": 382.43,
    "prev_close": 382.46,
    "change": -0.03,
    "change_pct": -0.0078,
    "name": "Tesla"
  },
  "INTC": {
    "price": 135.6401,
    "prev_close": 132.81,
    "change": 2.8301,
    "change_pct": 2.1309,
    "name": "Intel"
  },
  "NVDA": {
    "price": 201.1925,
    "prev_close": 200.9,
    "change": 0.2925,
    "change_pct": 0.1456,
    "name": "NVIDIA"
  },
  "SCHD": {
    "price": 31.735,
    "prev_close": 32.0301,
    "change": -0.2951,
    "change_pct": -0.9213,
    "name": "Schwab Dividend"
  },
  "FXAIX": {
    "price": 256.52,
    "prev_close": 260.25,
    "change": -3.73,
    "change_pct": -1.4332,
    "name": "Fidelity S&P 500"
  },
  "MAGS": {
    "price": 63.88,
    "prev_close": 63.3735,
    "change": 0.5065,
    "change_pct": 0.7992,
    "name": "Magnificent 7 ETF"
  },
  "FBTC": {
    "price": 52.95,
    "prev_close": 54.39,
    "change": -1.44,
    "change_pct": -2.6475,
    "name": "Fidelity Crypto"
  },
  "updated": "2026-06-24T15:04:41.934115+00:00"
}