{
  "TSLA": {
    "price": 376.3,
    "prev_close": 373.1799,
    "change": 3.1201,
    "change_pct": 0.8361,
    "name": "Tesla"
  },
  "INTC": {
    "price": 82.54,
    "prev_close": 80.1,
    "change": 2.44,
    "change_pct": 3.0462,
    "name": "Intel"
  },
  "NVDA": {
    "price": 208.27,
    "prev_close": 199.5,
    "change": 8.77,
    "change_pct": 4.396,
    "name": "NVIDIA"
  },
  "SCHD": {
    "price": 31.2,
    "prev_close": 31.4,
    "change": -0.2,
    "change_pct": -0.6369,
    "name": "Schwab Dividend"
  },
  "FXAIX": {
    "price": 247.04,
    "prev_close": 248.06,
    "change": -1.02,
    "change_pct": -0.4112,
    "name": "Fidelity S&P 500"
  },
  "MAGS": {
    "price": 66.57,
    "prev_close": 65.39,
    "change": 1.18,
    "change_pct": 1.8046,
    "name": "Magnificent 7 ETF"
  },
  "FBTC": {
    "price": 67.61,
    "prev_close": 68.2,
    "change": -0.59,
    "change_pct": -0.8651,
    "name": "Fidelity Crypto"
  },
  "updated": "2026-04-24T21:49:38.309211+00:00"
}