{
  "TSLA": {
    "price": 413.02,
    "prev_close": 404.68,
    "change": 8.34,
    "change_pct": 2.0609,
    "name": "Tesla"
  },
  "INTC": {
    "price": 118.31,
    "prev_close": 111.8693,
    "change": 6.4407,
    "change_pct": 5.7573,
    "name": "Intel"
  },
  "NVDA": {
    "price": 222.76,
    "prev_close": 221.54,
    "change": 1.22,
    "change_pct": 0.5507,
    "name": "NVIDIA"
  },
  "SCHD": {
    "price": 32.14,
    "prev_close": 32.1,
    "change": 0.04,
    "change_pct": 0.1246,
    "name": "Schwab Dividend"
  },
  "FXAIX": {
    "price": 255.78,
    "prev_close": 257.48,
    "change": -1.7,
    "change_pct": -0.6602,
    "name": "Fidelity S&P 500"
  },
  "MAGS": {
    "price": 69.24,
    "prev_close": 68.6,
    "change": 0.64,
    "change_pct": 0.9329,
    "name": "Magnificent 7 ETF"
  },
  "FBTC": {
    "price": 67.43,
    "prev_close": 66.7701,
    "change": 0.6599,
    "change_pct": 0.9883,
    "name": "Fidelity Crypto"
  },
  "updated": "2026-05-20T19:33:41.100646+00:00"
}