{
  "TSLA": {
    "price": 404.11,
    "prev_close": 409.4662,
    "change": -5.3562,
    "change_pct": -1.3081,
    "name": "Tesla"
  },
  "INTC": {
    "price": 110.8,
    "prev_close": 108.1401,
    "change": 2.6599,
    "change_pct": 2.4597,
    "name": "Intel"
  },
  "NVDA": {
    "price": 220.61,
    "prev_close": 222.75,
    "change": -2.14,
    "change_pct": -0.9607,
    "name": "NVIDIA"
  },
  "SCHD": {
    "price": 32.1,
    "prev_close": 32.07,
    "change": 0.03,
    "change_pct": 0.0935,
    "name": "Schwab Dividend"
  },
  "FXAIX": {
    "price": 257.48,
    "prev_close": 257.65,
    "change": -0.17,
    "change_pct": -0.066,
    "name": "Fidelity S&P 500"
  },
  "MAGS": {
    "price": 68.53,
    "prev_close": 69.6,
    "change": -1.07,
    "change_pct": -1.5374,
    "name": "Magnificent 7 ETF"
  },
  "FBTC": {
    "price": 66.82,
    "prev_close": 66.92,
    "change": -0.1,
    "change_pct": -0.1494,
    "name": "Fidelity Crypto"
  },
  "updated": "2026-05-19T20:51:02.227996+00:00"
}