{
  "TSLA": {
    "price": 395.34,
    "prev_close": 381.38,
    "change": 13.96,
    "change_pct": 3.6604,
    "name": "Tesla"
  },
  "INTC": {
    "price": 98.1501,
    "prev_close": 93.55,
    "change": 4.6001,
    "change_pct": 4.9173,
    "name": "Intel"
  },
  "NVDA": {
    "price": 199.93,
    "prev_close": 200.0097,
    "change": -0.0797,
    "change_pct": -0.0399,
    "name": "NVIDIA"
  },
  "SCHD": {
    "price": 31.895,
    "prev_close": 32.0893,
    "change": -0.1943,
    "change_pct": -0.6055,
    "name": "Schwab Dividend"
  },
  "FXAIX": {
    "price": 250.56,
    "prev_close": 248.01,
    "change": 2.55,
    "change_pct": 1.0282,
    "name": "Fidelity S&P 500"
  },
  "MAGS": {
    "price": 67.2701,
    "prev_close": 66.42,
    "change": 0.8501,
    "change_pct": 1.2799,
    "name": "Magnificent 7 ETF"
  },
  "FBTC": {
    "price": 68.25,
    "prev_close": 66.47,
    "change": 1.78,
    "change_pct": 2.6779,
    "name": "Fidelity Crypto"
  },
  "updated": "2026-05-01T17:37:28.000325+00:00"
}