{
  "TSLA": {
    "price": 391.87,
    "prev_close": 391.34,
    "change": 0.53,
    "change_pct": 0.1354,
    "name": "Tesla"
  },
  "INTC": {
    "price": 98.9197,
    "prev_close": 100.77,
    "change": -1.8503,
    "change_pct": -1.8362,
    "name": "Intel"
  },
  "NVDA": {
    "price": 197.9102,
    "prev_close": 198.13,
    "change": -0.2198,
    "change_pct": -0.1109,
    "name": "NVIDIA"
  },
  "SCHD": {
    "price": 31.64,
    "prev_close": 31.8595,
    "change": -0.2195,
    "change_pct": -0.689,
    "name": "Schwab Dividend"
  },
  "FXAIX": {
    "price": 251.3,
    "prev_close": 250.56,
    "change": 0.74,
    "change_pct": 0.2953,
    "name": "Fidelity S&P 500"
  },
  "MAGS": {
    "price": 67.2202,
    "prev_close": 66.8512,
    "change": 0.369,
    "change_pct": 0.552,
    "name": "Magnificent 7 ETF"
  },
  "FBTC": {
    "price": 70.06,
    "prev_close": 68.0109,
    "change": 2.0491,
    "change_pct": 3.0129,
    "name": "Fidelity Crypto"
  },
  "updated": "2026-05-04T14:53:45.140713+00:00"
}