{
  "TSLA": {
    "price": 420.0,
    "prev_close": 420.2483,
    "change": -0.2483,
    "change_pct": -0.0591,
    "name": "Tesla"
  },
  "INTC": {
    "price": 112.44,
    "prev_close": 110.613,
    "change": 1.827,
    "change_pct": 1.6517,
    "name": "Intel"
  },
  "NVDA": {
    "price": 220.12,
    "prev_close": 214.26,
    "change": 5.86,
    "change_pct": 2.735,
    "name": "NVIDIA"
  },
  "SCHD": {
    "price": 32.53,
    "prev_close": 32.44,
    "change": 0.09,
    "change_pct": 0.2774,
    "name": "Schwab Dividend"
  },
  "FXAIX": {
    "price": 262.86,
    "prev_close": 264.8,
    "change": -1.94,
    "change_pct": -0.7326,
    "name": "Fidelity S&P 500"
  },
  "MAGS": {
    "price": 69.24,
    "prev_close": 68.3,
    "change": 0.94,
    "change_pct": 1.3763,
    "name": "Magnificent 7 ETF"
  },
  "FBTC": {
    "price": 55.535,
    "prev_close": 55.8,
    "change": -0.265,
    "change_pct": -0.4749,
    "name": "Fidelity Crypto"
  },
  "updated": "2026-06-04T18:31:40.897509+00:00"
}