{
  "TSLA": {
    "price": 394.895,
    "prev_close": 408.87,
    "change": -13.975,
    "change_pct": -3.418,
    "name": "Tesla"
  },
  "INTC": {
    "price": 105.92,
    "prev_close": 109.8199,
    "change": -3.8999,
    "change_pct": -3.5512,
    "name": "Intel"
  },
  "NVDA": {
    "price": 205.79,
    "prev_close": 207.65,
    "change": -1.86,
    "change_pct": -0.8957,
    "name": "NVIDIA"
  },
  "SCHD": {
    "price": 32.235,
    "prev_close": 32.375,
    "change": -0.14,
    "change_pct": -0.4324,
    "name": "Schwab Dividend"
  },
  "FXAIX": {
    "price": 257.8,
    "prev_close": 257.02,
    "change": 0.78,
    "change_pct": 0.3035,
    "name": "Fidelity S&P 500"
  },
  "MAGS": {
    "price": 65.39,
    "prev_close": 66.2896,
    "change": -0.8996,
    "change_pct": -1.3571,
    "name": "Magnificent 7 ETF"
  },
  "FBTC": {
    "price": 53.77,
    "prev_close": 54.83,
    "change": -1.06,
    "change_pct": -1.9332,
    "name": "Fidelity Crypto"
  },
  "updated": "2026-06-09T19:47:20.537614+00:00"
}